fastdotcom2/__init__.py
fastdotcom2-0.0.19.dist-info/licenses/LICENSE
fastdotcom2-0.0.19.dist-info/METADATA
fastdotcom2-0.0.19.dist-info/WHEEL
fastdotcom2-0.0.19.dist-info/top_level.txt
fastdotcom2-0.0.19.dist-info/RECORD
