Metadata-Version: 2.4
Name: fastdotcom2
Version: 0.0.19
Summary: Python package to perform fast.com speedtest
Author: rosenrot
License: MIT
Project-URL: Homepage, https://github.com/rosenrot00/fastdotcom2
Project-URL: Issues, https://github.com/rosenrot00/fastdotcom2/issues
Classifier: Programming Language :: Python :: 3
Classifier: Operating System :: OS Independent
Requires-Python: >=3.8
License-File: LICENSE
Requires-Dist: icmplib>=3.0.0
Requires-Dist: requests>=2.32.3
Dynamic: license-file
